charizard_vla/__init__.py
charizard_vla/pokedex.py
charizard_vla/pokeegg.py
charizard_vla-0.2.7.dist-info/LICENSE
charizard_vla-0.2.7.dist-info/METADATA
charizard_vla-0.2.7.dist-info/WHEEL
charizard_vla-0.2.7.dist-info/entry_points.txt
charizard_vla-0.2.7.dist-info/top_level.txt
charizard_vla-0.2.7.dist-info/RECORD
