Metadata-Version: 2.1
Name: charizard-vla
Version: 0.2.7
Summary: VLA data processing package with polarization and self-calibration
Home-page: https://github.com/arpanastrobot/charizard-vla
Author: Arpan Pal
Author-email: arpan522000@gmail.com
Classifier: Development Status :: 3 - Alpha
Classifier: Intended Audience :: Science/Research
Classifier: Programming Language :: Python :: 3
Classifier: License :: OSI Approved :: MIT License
Classifier: Operating System :: OS Independent
Classifier: Topic :: Scientific/Engineering :: Astronomy
Requires-Python: >=3.6
License-File: LICENSE
